promptshield/__init__.py
promptshield/methods.py
promptshield/pattern_manager.py
promptshield/promptshield_boundary.py
promptshield/promptshield_report.py
promptshield/rate_limiting.py
promptshield/session_anomaly.py
promptshield/shields.py
promptshield/attack_db/benign/control.json
promptshield/attack_db/context_confusion/injection.json
promptshield/attack_db/control_plans/instruction_override.json
promptshield/attack_db/control_plans/persona_replacement.json
promptshield/attack_db/encoding/obfuscation.json
promptshield/attack_db/output_manipulation/format_forcing.json
promptshield/attack_db/payload_injection/data_hiding.json
promptshield/attack_db/policy_bypass/jailbreak.json
promptshield/attack_db/prompt_extraction/system_leak.json
promptshield/models/logistic_regression_expanded.pkl
promptshield/models/random_forest_expanded.pkl
promptshield/models/svm_expanded.pkl
promptshield/models/tfidf_vectorizer_expanded.pkl
promptshield/pii/__init__.py
promptshield/pii/contextual_detector.py
promptshield/pii/redaction.py
promptshield/security/__init__.py
promptshield/security/canary_crypto.py
promptshield/security/model_signing.py
promptshield/testing/__init__.py
promptshield/testing/evasion_tester.py
promptshield/training/__init__.py
promptshield/training/dataset_validator.py
promptshields-2.1.4.dist-info/licenses/LICENSE
promptshields-2.1.4.dist-info/METADATA
promptshields-2.1.4.dist-info/WHEEL
promptshields-2.1.4.dist-info/entry_points.txt
promptshields-2.1.4.dist-info/top_level.txt
promptshields-2.1.4.dist-info/RECORD
