Metadata-Version: 2.4
Name: promptshields
Version: 2.1.4
Summary: Production-Grade LLM Security Framework - Protect against prompt injection, jailbreaks, and data leakage
Home-page: https://github.com/Neural-alchemy/promptshield
Author: Neuralchemy
Author-email: Neuralchemy <security@neuralchemy.com>
Maintainer-email: Neuralchemy <security@neuralchemy.com>
License: MIT
Project-URL: Homepage, https://github.com/Neural-alchemy/promptshield
Project-URL: Documentation, https://github.com/Neural-alchemy/promptshield#documentation
Project-URL: Repository, https://github.com/Neural-alchemy/promptshield
Project-URL: Issues, https://github.com/Neural-alchemy/promptshield/issues
Project-URL: Changelog, https://github.com/Neural-alchemy/promptshield/releases
Keywords: llm,security,prompt-injection,jailbreak,ai-safety,guardrails,openai,langchain
Classifier: Development Status :: 5 - Production/Stable
Classifier: Intended Audience :: Developers
Classifier: Intended Audience :: Science/Research
Classifier: License :: OSI Approved :: MIT License
Classifier: Operating System :: OS Independent
Classifier: Programming Language :: Python :: 3
Classifier: Programming Language :: Python :: 3.8
Classifier: Programming Language :: Python :: 3.9
Classifier: Programming Language :: Python :: 3.10
Classifier: Programming Language :: Python :: 3.11
Classifier: Programming Language :: Python :: 3.12
Classifier: Topic :: Security
Classifier: Topic :: Scientific/Engineering :: Artificial Intelligence
Classifier: Topic :: Software Development :: Libraries :: Python Modules
Requires-Python: >=3.8
License-File: LICENSE
Requires-Dist: numpy>=1.20.0
Requires-Dist: scikit-learn>=1.0.0
Requires-Dist: cryptography>=3.4.0
Provides-Extra: dev
Requires-Dist: pytest>=7.0.0; extra == "dev"
Requires-Dist: pytest-cov>=3.0.0; extra == "dev"
Requires-Dist: black>=22.0.0; extra == "dev"
Requires-Dist: flake8>=4.0.0; extra == "dev"
Requires-Dist: mypy>=0.950; extra == "dev"
Provides-Extra: ml
Requires-Dist: xgboost>=1.5.0; extra == "ml"
Requires-Dist: sentence-transformers>=2.2.0; extra == "ml"
Provides-Extra: all
Requires-Dist: promptshield[dev,ml]; extra == "all"
Dynamic: author
Dynamic: home-page
Dynamic: license-file
Dynamic: requires-python
